{"itemid":1931,"subject":"Not in San Diego","event":"I hope that everyone in San Diego is having fun at Comicon.  HBO has a big presence there, I know, and a lot of our cast are on hand for the GAME OF THRONES panel and the usual endless rounds of signings and interviews.   Also, Bantam is bringing out the 2017 ICE & FIRE calendar, which is always a great event.  And Gary Gianni, who illustrated THE KNIGHT OF THE SEVEN KINGDOMS, has a table and is selling a cool new sketchbook of his artwork.  \r\n\r\nMakes me wish I could be there as well.\r\n\r\nBut I'm not.\r\n\r\nNow, normally, I would not feel the need to post about where I'm not and what I am not doing... only I am getting reports from friends in San Diego, and friends of friends, that I have been sighted at the con.\r\n\r\nIt's not me.\r\n\r\nReally.  It's not.   It's some other old fat guy in a Greek sailor's cap and pair of suspenders, maybe.  Who may or may not be consciously cosplaying as me.   \r\n\r\n((And you have no idea how weird it feels to be typing that sentence.  Way back when the show was first starting, there were a couple of Daenerys Targaryen cosplayers at San Diego, and I thought that was way cool.  Fans dressing up as my characters, hey, hot damn!  Never in my wildest dreams did I imagine that anyone would ever want to dress up as <i><b>me</b></i>.  But now I seem to encounter it wherever I go.  Witness this picture from my 2013 trip to Australia.\r\n\r\n<img src=\"http://ic.pics.livejournal.com/grrm/7059164/374363/374363_800.jpg\" alt=\"\" title=\"\">\r\n\r\nAnyway... just for the record... I have a big Wild Cards event at the Jean Cocteau Cinema this weekend, with nineteen writers turning up from all across the country, so as much as I would like to be at comicon, <i><b>I am not ther</b></i>e.   Accept no substitutes!!\r\n\r\n((And just to be clear, no, I do not disappove of fans cosplaying as me.  I do find it surreal, but hey, what they hell, have fun... so long as they don't actually pretend to <i><b>be</b></i> me)).\r\n\r\n Moving right along... one thing that is at comicon is the new ICE & FIRE calendar, with art by Didier Graffet.  It's gorgeous.   Grab a copy if you're at the con.  And if not, the calendar should be available at your favorite local bookstore or online bookseller, and will certainly be available through the Jean Cocteau.\r\n\r\n<img src=\"http://ic.pics.livejournal.com/grrm/7059164/374765/374765_900.jpg\" alt=\"\" title=\"\">","ditemid":494398,"eventtime":"2016-07-22 14:46:00","props":{"current_mood":"amused","current_location":"Santa Fe","taglist":"travels, bantam spectra, comicon, calendar","crosspost_tw_log":"[Fri Jul 22 20:46:21 2016]R [Fri Jul 22 20:46:23 2016]https://twitter.com/GRRMspeaking/status/756591242096500736 ","current_moodid":44,"homepage_reposted":63986505,"commentalter":1469574065,"opt_lockcomments":1,"crosspost_tw":"https://twitter.com/GRRMspeaking/status/756591242096500736","picture_keyword":"hiya hiya hiya","opt_screening":"F","revnum":1,"personifi_tags":"nterms:yes","interface":"web","langs":"{\"languages\":[[\"eng\",0.655628656820009]],\"detector\":\"Lingua-YALI:0.015\",\"updated\":1469220402}","revtime":1469574137},"can_comment":0,"logtime":"2016-07-22 20:46:18","anum":62,"url":"http://grrm.livejournal.com/494398.html","event_timestamp":1469198760,"reply_count":39,"comments":[{"collapsed":0,"shown":1,"userpic":"http://l-userpic.livejournal.com/108670455/8291597","actions":[{"allowed":1,"href":"http://grrm.livejournal.com/494398.html?thread=24792638#t24792638","name":"permalink","title":"link"},{"allowed":1,"href":"http://grrm.livejournal.com/494398.html?thread=24792638#t24792638","name":"collapse","title":"Collapse"},{"allowed":1,"href":"http://grrm.livejournal.com/494398.html?thread=24792638#t24792638","name":"expand","title":"Expand"}],"uname":"missfragout","loaded":1,"p_tracked":0,"commenter_journal_base":"http://missfragout.livejournal.com/","statprefix":"http://l-stat.livejournal.net","dtalkid":24792638,"talkid":96846,"thread_url":"http://grrm.livejournal.com/494398.html?thread=24792638#t24792638","article":"That calendar is gorgeous! Will definitely buy it :)","upictitle":"...: Schmetterling","siteroot":"http://www.livejournal.com","stime":"9 months ago","poster":"grrm","ctime":"July 22 2016, 20:54:38 UTC","massactions":0,"subject":"","deleted":0,"username":[{"journal_url":"http://missfragout.livejournal.com/","striked":null,"journaltype":"P","userhead_url":"http://l-stat.livejournal.net/img/userinfo_v8.svg?v=17080?v=146.10","color":null,"noctxpopup":0,"side_alias":0,"journal":"missfragout","inline_css":0,"attrs":null,"is_identity":0,"bold":1,"show_userhead":1,"username":"missfragout","user_alias":"","profile_url":"http://missfragout.livejournal.com/profile","alias":0}],"dname":"missfragout","ctime_ts":1469220878,"tracked":0},{"shown":1,"collapsed":0,"userpic":"http://l-userpic.livejournal.com/35606426/503242","actions":[{"allowed":1,"href":"http://grrm.livejournal.com/494398.html?thread=24792894#t24792894","name":"permalink","title":"link"},{"allowed":1,"href":"http://grrm.livejournal.com/494398.html?thread=24792894#t24792894","name":"collapse","title":"Collapse"},{"allowed":1,"href":"http://grrm.livejournal.com/494398.html?thread=24792894#t24792894","name":"expand","title":"Expand"}],"uname":"loree","loaded":1,"p_tracked":0,"commenter_journal_base":"http://loree.livejournal.com/","statprefix":"http://l-stat.livejournal.net","dtalkid":24792894,"talkid":96847,"thread_url":"http://grrm.livejournal.com/494398.html?thread=24792894#t24792894","upictitle":"Loree: shades","article":"Amusingly, I had a pre-con nightmare before you joined us at Norwescon last year involving someone cosplaying as you.","siteroot":"http://www.livejournal.com","poster":"grrm","stime":"9 months ago","ctime":"July 22 2016, 20:55:54 UTC","massactions":0,"subject":"","deleted":0,"username":[{"journal_url":"http://loree.livejournal.com/","striked":null,"journaltype":"P","userhead_url":"http://l-stat.livejournal.net/img/userinfo_v8.svg?v=17080?v=146.10","color":null,"noctxpopup":0,"side_alias":0,"journal":"loree","inline_css":0,"attrs":null,"is_identity":0,"bold":1,"show_userhead":1,"username":"loree","user_alias":"","profile_url":"http://loree.livejournal.com/profile","alias":0}],"dname":"loree","ctime_ts":1469220954,"tracked":0},{"shown":1,"collapsed":0,"userpic":"http://l-userpic.livejournal.com/126309515/78162872","actions":[{"allowed":1,"href":"http://grrm.livejournal.com/494398.html?thread=24793150#t24793150","name":"permalink","title":"link"},{"allowed":1,"href":"http://grrm.livejournal.com/494398.html?thread=24793150#t24793150","name":"collapse","title":"Collapse"},{"allowed":1,"href":"http://grrm.livejournal.com/494398.html?thread=24793150#t24793150","name":"expand","title":"Expand"}],"uname":"ext_3731902","loaded":1,"p_tracked":0,"commenter_journal_base":"http://twitter.com/DeHieloyFuego","statprefix":"http://l-stat.livejournal.net","dtalkid":24793150,"talkid":96848,"etime_ts":"1469222108","thread_url":"http://grrm.livejournal.com/494398.html?thread=24793150#t24793150","upictitle":"@lfonso.cabello ツ: pic#126309515","article":"But he doesn't write like you, <br />In fact , no one writes like you, maybe as well, but different. Now I'm reading historic novel about Ancient Rome (Trajano's Trilogy)and this, thaks your books. After all history is the source of your books. Thanks!<br />","siteroot":"http://www.livejournal.com","poster":"grrm","stime":"9 months ago","ctime":"July 22 2016, 21:12:55 UTC","massactions":0,"subject":"But he doesn&#39;t write like you","deleted":0,"username":[{"journal_url":"http://twitter.com/DeHieloyFuego","striked":null,"journaltype":"I","userhead_url":"http://l-stat.livejournal.net/img/icons/twitter-16.png?v=29916?v=146.10","color":null,"noctxpopup":0,"side_alias":0,"journal":"DeHieloyFuego","inline_css":0,"attrs":null,"is_identity":1,"bold":1,"show_userhead":1,"username":"ext_3731902","user_alias":"","profile_url":"http://www.livejournal.com/profile?userid=78162872&t=I","alias":0}],"etime":"July 22 2016, 21:15:08 UTC","dname":"DeHieloyFuego","ctime_ts":1469221975,"tracked":0},{"shown":1,"collapsed":0,"actions":[{"allowed":1,"href":"http://grrm.livejournal.com/494398.html?thread=24793406#t24793406","name":"permalink","title":"link"},{"allowed":1,"href":"http://grrm.livejournal.com/494398.html?thread=24793406#t24793406","name":"collapse","title":"Collapse"},{"allowed":1,"href":"http://grrm.livejournal.com/494398.html?thread=24793406#t24793406","name":"expand","title":"Expand"}],"uname":"ext_3755314","loaded":1,"p_tracked":0,"commenter_journal_base":"https://plus.google.com/107237008952709984372","statprefix":"http://l-stat.livejournal.net","dtalkid":24793406,"talkid":96849,"thread_url":"http://grrm.livejournal.com/494398.html?thread=24793406#t24793406","upictitle":"Alex Felix: pic#0","article":"That's hilarious! It's almost like the incident where Bryan Cranston went to Comic Con and walked the show floor wearing the Walter White mask. No one even thought to bat an eye and question it. Even Matt Smith did the same wearing a Bart Simpson mask while walking the show floor.","siteroot":"http://www.livejournal.com","poster":"grrm","stime":"9 months ago","ctime":"July 22 2016, 21:16:19 UTC","massactions":0,"subject":"","deleted":0,"username":[{"journal_url":"https://plus.google.com/107237008952709984372","striked":null,"journaltype":"I","userhead_url":"http://l-stat.livejournal.net/img/icons/google-16.png?v=29916?v=146.10","color":null,"noctxpopup":0,"side_alias":0,"journal":"Alex Felix","inline_css":0,"attrs":null,"is_identity":1,"bold":1,"show_userhead":1,"username":"ext_3755314","user_alias":"","profile_url":"http://www.livejournal.com/profile?userid=78230768&t=I","alias":0}],"dname":"Alex Felix","ctime_ts":1469222179,"tracked":0},{"shown":1,"collapsed":0,"userpic":"http://l-userpic.livejournal.com/46721543/2854335","actions":[{"allowed":1,"href":"http://grrm.livejournal.com/494398.html?thread=24793662#t24793662","name":"permalink","title":"link"},{"allowed":1,"href":"http://grrm.livejournal.com/494398.html?thread=24793662#t24793662","name":"collapse","title":"Collapse"},{"allowed":1,"href":"http://grrm.livejournal.com/494398.html?thread=24793662#t24793662","name":"expand","title":"Expand"}],"uname":"kalimac","loaded":1,"p_tracked":0,"commenter_journal_base":"http://kalimac.livejournal.com/","statprefix":"http://l-stat.livejournal.net","dtalkid":24793662,"talkid":96850,"thread_url":"http://grrm.livejournal.com/494398.html?thread=24793662#t24793662","upictitle":"Kalimac: puzzle","article":"<i>I</i> am also an old fat guy with a Greek sailor's cap and a pair of suspenders, though my beard is not yet as white as yours.  But I'm not at Comicon either!","siteroot":"http://www.livejournal.com","poster":"grrm","stime":"9 months ago","ctime":"July 22 2016, 21:25:18 UTC","massactions":0,"subject":"","deleted":0,"username":[{"journal_url":"http://kalimac.livejournal.com/","striked":null,"journaltype":"P","userhead_url":"http://l-stat.livejournal.net/img/userinfo_v8.svg?v=17080?v=146.10","color":null,"noctxpopup":0,"side_alias":0,"journal":"kalimac","inline_css":0,"attrs":null,"is_identity":0,"bold":1,"show_userhead":1,"username":"kalimac","user_alias":"","profile_url":"http://kalimac.livejournal.com/profile","alias":0}],"dname":"kalimac","ctime_ts":1469222718,"tracked":0},{"shown":1,"collapsed":0,"userpic":"http://l-userpic.livejournal.com/126349678/78230815","actions":[{"allowed":1,"href":"http://grrm.livejournal.com/494398.html?thread=24793918#t24793918","name":"permalink","title":"link"},{"allowed":1,"href":"http://grrm.livejournal.com/494398.html?thread=24793918#t24793918","name":"collapse","title":"Collapse"},{"allowed":1,"href":"http://grrm.livejournal.com/494398.html?thread=24793918#t24793918","name":"expand","title":"Expand"}],"uname":"ext_3755325","loaded":1,"p_tracked":0,"commenter_journal_base":"https://www.facebook.com/app_scoped_user_id/10208390251687573/","statprefix":"http://l-stat.livejournal.net","dtalkid":24793918,"talkid":96851,"thread_url":"http://grrm.livejournal.com/494398.html?thread=24793918#t24793918","upictitle":"Parvez Raj: pic#126349678","article":"Hello George, big fan! Are you planning to come to Canada anytime soon?","siteroot":"http://www.livejournal.com","poster":"grrm","stime":"9 months ago","ctime":"July 22 2016, 21:27:29 UTC","massactions":0,"subject":"Canada ","deleted":0,"username":[{"journal_url":"https://www.facebook.com/app_scoped_user_id/10208390251687573/","striked":null,"journaltype":"I","userhead_url":"http://l-stat.livejournal.net/img/icons/facebook-16.png?v=29916?v=146.10","color":null,"noctxpopup":0,"side_alias":0,"journal":"Parvez Raj","inline_css":0,"attrs":null,"is_identity":1,"bold":1,"show_userhead":1,"username":"ext_3755325","user_alias":"","profile_url":"http://www.livejournal.com/profile?userid=78230815&t=I","alias":0}],"dname":"Parvez Raj","ctime_ts":1469222849,"tracked":0},{"shown":1,"collapsed":0,"userpic":"http://l-userpic.livejournal.com/126340786/78214856","actions":[{"allowed":1,"href":"http://grrm.livejournal.com/494398.html?thread=24794174#t24794174","name":"permalink","title":"link"},{"allowed":1,"href":"http://grrm.livejournal.com/494398.html?thread=24794174#t24794174","name":"collapse","title":"Collapse"},{"allowed":1,"href":"http://grrm.livejournal.com/494398.html?thread=24794174#t24794174","name":"expand","title":"Expand"}],"uname":"ext_3750074","loaded":1,"p_tracked":0,"commenter_journal_base":"https://www.facebook.com/app_scoped_user_id/274008086290423/","statprefix":"http://l-stat.livejournal.net","dtalkid":24794174,"talkid":96852,"etime_ts":"1469223001","thread_url":"http://grrm.livejournal.com/494398.html?thread=24794174#t24794174","upictitle":"Damon McAllister: pic#126340786","article":"The Others and their countless minions - the wights, are described as having pale blue eyes. Coldhands, on the other hand, identified by Sam as a wight, and confirmed to be undead by Leaf and Bloodraven, shares some of the characteristics of a wight (pale skin, cold black hands, etc). But he's described as having black eyes that resemble a raven's. So, my question is - are the blue eyes associated with regular wights a sign of being controlled by the Others?","siteroot":"http://www.livejournal.com","poster":"grrm","stime":"9 months ago","ctime":"July 22 2016, 21:28:26 UTC","massactions":0,"subject":"The Others, Coldhands","deleted":0,"username":[{"journal_url":"https://www.facebook.com/app_scoped_user_id/274008086290423/","striked":null,"journaltype":"I","userhead_url":"http://l-stat.livejournal.net/img/icons/facebook-16.png?v=29916?v=146.10","color":null,"noctxpopup":0,"side_alias":0,"journal":"Damon McAllister","inline_css":0,"attrs":null,"is_identity":1,"bold":1,"show_userhead":1,"username":"ext_3750074","user_alias":"","profile_url":"http://www.livejournal.com/profile?userid=78214856&t=I","alias":0}],"etime":"July 22 2016, 21:30:01 UTC","dname":"Damon McAllister","ctime_ts":1469222906,"tracked":0},{"shown":1,"collapsed":0,"userpic":"http://l-userpic.livejournal.com/123057959/69751082","actions":[{"allowed":1,"href":"http://grrm.livejournal.com/494398.html?thread=24794430#t24794430","name":"permalink","title":"link"},{"allowed":1,"href":"http://grrm.livejournal.com/494398.html?thread=24794430#t24794430","name":"collapse","title":"Collapse"},{"allowed":1,"href":"http://grrm.livejournal.com/494398.html?thread=24794430#t24794430","name":"expand","title":"Expand"}],"uname":"ext_2507276","loaded":1,"p_tracked":0,"commenter_journal_base":"https://www.facebook.com/steve.huntsinger","statprefix":"http://l-stat.livejournal.net","dtalkid":24794430,"talkid":96853,"thread_url":"http://grrm.livejournal.com/494398.html?thread=24794430#t24794430","upictitle":"Steven James: pic#123057959","article":"Not sure if this has been answered elsewhere, but will this new calendar have any depictions of WINDS content as with last year's calendar?<br /><br />Cheers!","siteroot":"http://www.livejournal.com","poster":"grrm","stime":"9 months ago","ctime":"July 23 2016, 02:38:10 UTC","massactions":0,"subject":"Calender","deleted":0,"username":[{"journal_url":"https://www.facebook.com/steve.huntsinger","striked":null,"journaltype":"I","userhead_url":"http://l-stat.livejournal.net/img/icons/facebook-16.png?v=29916?v=146.10","color":null,"noctxpopup":0,"side_alias":0,"journal":"Steven James","inline_css":0,"attrs":null,"is_identity":1,"bold":1,"show_userhead":1,"username":"ext_2507276","user_alias":"","profile_url":"http://www.livejournal.com/profile?userid=69751082&t=I","alias":0}],"dname":"Steven James","ctime_ts":1469241490,"tracked":0},{"shown":1,"collapsed":0,"userpic":"http://l-userpic.livejournal.com/117796605/50627511","actions":[{"allowed":1,"href":"http://grrm.livejournal.com/494398.html?thread=24794686#t24794686","name":"permalink","title":"link"},{"allowed":1,"href":"http://grrm.livejournal.com/494398.html?thread=24794686#t24794686","name":"collapse","title":"Collapse"},{"allowed":1,"href":"http://grrm.livejournal.com/494398.html?thread=24794686#t24794686","name":"expand","title":"Expand"}],"uname":"ext_1271338","loaded":1,"p_tracked":0,"commenter_journal_base":"http://twitter.com/RaUL_AMDERLAINE","statprefix":"http://l-stat.livejournal.net","dtalkid":24794686,"talkid":96854,"thread_url":"http://grrm.livejournal.com/494398.html?thread=24794686#t24794686","upictitle":"RaUL AMDERLAINE: pic#117796605","article":"<br />Yeah, but how can we be sure that the real you is not the guy at Comicon and the fake you, the guy writing this blog post?","siteroot":"http://www.livejournal.com","poster":"grrm","stime":"9 months ago","ctime":"July 23 2016, 03:00:31 UTC","massactions":0,"subject":"","deleted":0,"username":[{"journal_url":"http://twitter.com/RaUL_AMDERLAINE","striked":null,"journaltype":"I","userhead_url":"http://l-stat.livejournal.net/img/icons/twitter-16.png?v=29916?v=146.10","color":null,"noctxpopup":0,"side_alias":0,"journal":"RaUL_AMDERLAINE","inline_css":0,"attrs":null,"is_identity":1,"bold":1,"show_userhead":1,"username":"ext_1271338","user_alias":"","profile_url":"http://www.livejournal.com/profile?userid=50627511&t=I","alias":0}],"dname":"RaUL_AMDERLAINE","ctime_ts":1469242831,"tracked":0},{"shown":1,"collapsed":0,"userpic":"http://l-userpic.livejournal.com/125735980/77258680","actions":[{"allowed":1,"href":"http://grrm.livejournal.com/494398.html?thread=24795454#t24795454","name":"permalink","title":"link"},{"allowed":1,"href":"http://grrm.livejournal.com/494398.html?thread=24795454#t24795454","name":"collapse","title":"Collapse"},{"allowed":1,"href":"http://grrm.livejournal.com/494398.html?thread=24795454#t24795454","name":"expand","title":"Expand"}],"uname":"ext_3454866","loaded":1,"p_tracked":0,"commenter_journal_base":"https://www.facebook.com/app_scoped_user_id/10153776149104014/","statprefix":"http://l-stat.livejournal.net","dtalkid":24795454,"talkid":96857,"thread_url":"http://grrm.livejournal.com/494398.html?thread=24795454#t24795454","above":24794686,"upictitle":"Luke Teeninga: pic#125735980","article":"It would still be true when fake George writes \"I am not at Comicon\"! :-P","siteroot":"http://www.livejournal.com","poster":"grrm","stime":"9 months ago","ctime":"July 23 2016, 12:21:52 UTC","parent":24794686,"massactions":0,"subject":"","deleted":0,"username":[{"journal_url":"https://www.facebook.com/app_scoped_user_id/10153776149104014/","striked":null,"journaltype":"I","userhead_url":"http://l-stat.livejournal.net/img/icons/facebook-16.png?v=29916?v=146.10","color":null,"noctxpopup":0,"side_alias":0,"journal":"Luke Teeninga","inline_css":0,"attrs":null,"is_identity":1,"bold":1,"show_userhead":1,"username":"ext_3454866","user_alias":"","profile_url":"http://www.livejournal.com/profile?userid=77258680&t=I","alias":0}],"dname":"Luke Teeninga","ctime_ts":1469276512,"tracked":0},{"shown":1,"collapsed":0,"userpic":"http://l-userpic.livejournal.com/114963995/14866583","actions":[{"allowed":1,"href":"http://grrm.livejournal.com/494398.html?thread=24794942#t24794942","name":"permalink","title":"link"},{"allowed":1,"href":"http://grrm.livejournal.com/494398.html?thread=24794942#t24794942","name":"collapse","title":"Collapse"},{"allowed":1,"href":"http://grrm.livejournal.com/494398.html?thread=24794942#t24794942","name":"expand","title":"Expand"}],"uname":"noybusiness","loaded":1,"p_tracked":0,"commenter_journal_base":"http://noybusiness.livejournal.com/","statprefix":"http://l-stat.livejournal.net","dtalkid":24794942,"talkid":96855,"thread_url":"http://grrm.livejournal.com/494398.html?thread=24794942#t24794942","upictitle":"noybusiness: never seen an elephant fly","article":"Didier Graffet is a great artist, and extremely patient. At the 2013 World Fantasy Convention, which was in Brighton that year, he signed both mine and my Mom's convention books and made two detailed illustrations, which he copied exactly in each. A dragon and a seaside castle.","siteroot":"http://www.livejournal.com","poster":"grrm","stime":"9 months ago","ctime":"July 23 2016, 03:40:04 UTC","massactions":0,"subject":"","deleted":0,"username":[{"journal_url":"http://noybusiness.livejournal.com/","striked":null,"journaltype":"P","userhead_url":"http://l-stat.livejournal.net/img/userinfo_v8.svg?v=17080?v=146.10","color":null,"noctxpopup":0,"side_alias":0,"journal":"noybusiness","inline_css":0,"attrs":null,"is_identity":0,"bold":1,"show_userhead":1,"username":"noybusiness","user_alias":"","profile_url":"http://noybusiness.livejournal.com/profile","alias":0}],"dname":"noybusiness","ctime_ts":1469245204,"tracked":0},{"shown":1,"collapsed":0,"userpic":"http://l-userpic.livejournal.com/126300450/78147668","actions":[{"allowed":1,"href":"http://grrm.livejournal.com/494398.html?thread=24795198#t24795198","name":"permalink","title":"link"},{"allowed":1,"href":"http://grrm.livejournal.com/494398.html?thread=24795198#t24795198","name":"collapse","title":"Collapse"},{"allowed":1,"href":"http://grrm.livejournal.com/494398.html?thread=24795198#t24795198","name":"expand","title":"Expand"}],"uname":"ext_3726554","loaded":1,"p_tracked":0,"commenter_journal_base":"http://twitter.com/HenrikBreines","statprefix":"http://l-stat.livejournal.net","dtalkid":24795198,"talkid":96856,"thread_url":"http://grrm.livejournal.com/494398.html?thread=24795198#t24795198","upictitle":"Henrik Breines: pic#126300450","article":"The calendar looks cool! Do you listen to music while you write, George?","siteroot":"http://www.livejournal.com","poster":"grrm","stime":"9 months ago","ctime":"July 23 2016, 08:40:07 UTC","massactions":0,"subject":"","deleted":0,"username":[{"journal_url":"http://twitter.com/HenrikBreines","striked":null,"journaltype":"I","userhead_url":"http://l-stat.livejournal.net/img/icons/twitter-16.png?v=29916?v=146.10","color":null,"noctxpopup":0,"side_alias":0,"journal":"HenrikBreines","inline_css":0,"attrs":null,"is_identity":1,"bold":1,"show_userhead":1,"username":"ext_3726554","user_alias":"","profile_url":"http://www.livejournal.com/profile?userid=78147668&t=I","alias":0}],"dname":"HenrikBreines","ctime_ts":1469263207,"tracked":0},{"shown":1,"collapsed":0,"userpic":"http://l-userpic.livejournal.com/98605106/11925761","actions":[{"allowed":1,"href":"http://grrm.livejournal.com/494398.html?thread=24795710#t24795710","name":"permalink","title":"link"},{"allowed":1,"href":"http://grrm.livejournal.com/494398.html?thread=24795710#t24795710","name":"collapse","title":"Collapse"},{"allowed":1,"href":"http://grrm.livejournal.com/494398.html?thread=24795710#t24795710","name":"expand","title":"Expand"}],"uname":"sue_bursztynski","loaded":1,"p_tracked":0,"commenter_journal_base":"http://sue-bursztynski.livejournal.com/","statprefix":"http://l-stat.livejournal.net","dtalkid":24795710,"talkid":96858,"thread_url":"http://grrm.livejournal.com/494398.html?thread=24795710#t24795710","upictitle":"sue_bursztynski: pic#98605106","article":"Very strange! So, neither of the guys in the picture is you? And where in Australia were you? One of the bigger cons, I suppose? I recall the only time I ever met you was in the foyer of a tiny hotel in St Kilda back when you had just written Fevre Dream and it was about to be published. I can't recall which con it was. We had a few at that hotel. <br /><br />A totally irrelevant comment which may amuse you. One of my workmates, an Indian lady, told me proudly about her new granddaughter. \"Her name is Arya,\" she said, \"after the Indian goddess who fights demons.\" The next time I saw her, she said disgustedly that she had been told that no, the baby was not named for an Indian goddess but the girl in GoT! Oh, well. ","siteroot":"http://www.livejournal.com","poster":"grrm","stime":"9 months ago","ctime":"July 23 2016, 13:04:15 UTC","massactions":0,"subject":"","deleted":0,"username":[{"journal_url":"http://sue-bursztynski.livejournal.com/","striked":null,"journaltype":"P","userhead_url":"http://l-stat.livejournal.net/img/userinfo_v8.svg?v=17080?v=146.10","color":null,"noctxpopup":0,"side_alias":0,"journal":"sue_bursztynski","inline_css":0,"attrs":null,"is_identity":0,"bold":1,"show_userhead":1,"username":"sue_bursztynski","user_alias":"","profile_url":"http://sue-bursztynski.livejournal.com/profile","alias":0}],"dname":"sue_bursztynski","ctime_ts":1469279055,"tracked":0},{"shown":1,"collapsed":0,"userpic":"http://l-userpic.livejournal.com/125840536/77414429","actions":[{"allowed":1,"href":"http://grrm.livejournal.com/494398.html?thread=24795966#t24795966","name":"permalink","title":"link"},{"allowed":1,"href":"http://grrm.livejournal.com/494398.html?thread=24795966#t24795966","name":"collapse","title":"Collapse"},{"allowed":1,"href":"http://grrm.livejournal.com/494398.html?thread=24795966#t24795966","name":"expand","title":"Expand"}],"uname":"ext_3499170","loaded":1,"p_tracked":0,"commenter_journal_base":"https://www.facebook.com/app_scoped_user_id/1039883112742073/","statprefix":"http://l-stat.livejournal.net","dtalkid":24795966,"talkid":96859,"thread_url":"http://grrm.livejournal.com/494398.html?thread=24795966#t24795966","upictitle":"Ahsan Syed: pic#125840536","article":"Hey George, is your favorite character in ASOIAF different from the character you most enjoy writing? ","siteroot":"http://www.livejournal.com","poster":"grrm","stime":"9 months ago","ctime":"July 23 2016, 13:50:36 UTC","massactions":0,"subject":"","deleted":0,"username":[{"journal_url":"https://www.facebook.com/app_scoped_user_id/1039883112742073/","striked":null,"journaltype":"I","userhead_url":"http://l-stat.livejournal.net/img/icons/facebook-16.png?v=29916?v=146.10","color":null,"noctxpopup":0,"side_alias":0,"journal":"Ahsan Syed","inline_css":0,"attrs":null,"is_identity":1,"bold":1,"show_userhead":1,"username":"ext_3499170","user_alias":"","profile_url":"http://www.livejournal.com/profile?userid=77414429&t=I","alias":0}],"dname":"Ahsan Syed","ctime_ts":1469281836,"tracked":0},{"shown":1,"collapsed":0,"userpic":"http://l-userpic.livejournal.com/126351005/78233071","actions":[{"allowed":1,"href":"http://grrm.livejournal.com/494398.html?thread=24796222#t24796222","name":"permalink","title":"link"},{"allowed":1,"href":"http://grrm.livejournal.com/494398.html?thread=24796222#t24796222","name":"collapse","title":"Collapse"},{"allowed":1,"href":"http://grrm.livejournal.com/494398.html?thread=24796222#t24796222","name":"expand","title":"Expand"}],"uname":"ext_3756015","loaded":1,"p_tracked":0,"commenter_journal_base":"http://twitter.com/Goreanguy","statprefix":"http://l-stat.livejournal.net","dtalkid":24796222,"talkid":96860,"thread_url":"http://grrm.livejournal.com/494398.html?thread=24796222#t24796222","upictitle":"Marcus L: pic#126351005","article":"Idea:<br /><br />Hire a guy to be you at conventions, while you write books!","siteroot":"http://www.livejournal.com","poster":"grrm","stime":"9 months ago","ctime":"July 23 2016, 15:30:21 UTC","massactions":0,"subject":"Hire him!","deleted":0,"username":[{"journal_url":"http://twitter.com/Goreanguy","striked":null,"journaltype":"I","userhead_url":"http://l-stat.livejournal.net/img/icons/twitter-16.png?v=29916?v=146.10","color":null,"noctxpopup":0,"side_alias":0,"journal":"Goreanguy","inline_css":0,"attrs":null,"is_identity":1,"bold":1,"show_userhead":1,"username":"ext_3756015","user_alias":"","profile_url":"http://www.livejournal.com/profile?userid=78233071&t=I","alias":0}],"dname":"Goreanguy","ctime_ts":1469287821,"tracked":0},{"shown":1,"collapsed":0,"userpic":"http://l-userpic.livejournal.com/126280755/78115882","actions":[{"allowed":1,"href":"http://grrm.livejournal.com/494398.html?thread=24796478#t24796478","name":"permalink","title":"link"},{"allowed":1,"href":"http://grrm.livejournal.com/494398.html?thread=24796478#t24796478","name":"collapse","title":"Collapse"},{"allowed":1,"href":"http://grrm.livejournal.com/494398.html?thread=24796478#t24796478","name":"expand","title":"Expand"}],"uname":"olliethehound","loaded":1,"p_tracked":0,"commenter_journal_base":"http://olliethehound.livejournal.com/","statprefix":"http://l-stat.livejournal.net","dtalkid":24796478,"talkid":96861,"thread_url":"http://grrm.livejournal.com/494398.html?thread=24796478#t24796478","upictitle":"olliethehound: pic#126280755","article":"Sigh. There are countless articles online, \"trash\" articles I suppose, about you planning on releasing Winds of Winter and A Dream of Spring together. <br />  after reading through those ridiculous articles, I felt bad for you mr. Martin. so many folks out there are just crazy and spread such false messages about you! The \"information\" age, eh? Lol. I can only imagine.<br /><br />I got a kick out of that man who cosplayed as you, he did a good you! That's got to be a strange feeling. It's probably good I'm not at the con, I would have been fooled and asked for their autograph. ","siteroot":"http://www.livejournal.com","poster":"grrm","stime":"9 months ago","ctime":"July 23 2016, 16:28:14 UTC","massactions":0,"subject":"","deleted":0,"username":[{"journal_url":"http://olliethehound.livejournal.com/","striked":null,"journaltype":"P","userhead_url":"http://l-stat.livejournal.net/img/userinfo_v8.svg?v=17080?v=146.10","color":null,"noctxpopup":0,"side_alias":0,"journal":"olliethehound","inline_css":0,"attrs":null,"is_identity":0,"bold":1,"show_userhead":1,"username":"olliethehound","user_alias":"","profile_url":"http://olliethehound.livejournal.com/profile","alias":0}],"dname":"olliethehound","ctime_ts":1469291294,"tracked":0},{"shown":1,"collapsed":0,"userpic":"http://l-userpic.livejournal.com/126351506/78233767","actions":[{"allowed":1,"href":"http://grrm.livejournal.com/494398.html?thread=24796734#t24796734","name":"permalink","title":"link"},{"allowed":1,"href":"http://grrm.livejournal.com/494398.html?thread=24796734#t24796734","name":"collapse","title":"Collapse"},{"allowed":1,"href":"http://grrm.livejournal.com/494398.html?thread=24796734#t24796734","name":"expand","title":"Expand"}],"uname":"ext_3756308","loaded":1,"p_tracked":0,"commenter_journal_base":"https://www.facebook.com/app_scoped_user_id/10154168127740831/","statprefix":"http://l-stat.livejournal.net","dtalkid":24796734,"talkid":96862,"thread_url":"http://grrm.livejournal.com/494398.html?thread=24796734#t24796734","upictitle":"Riley Kearns: pic#126351506","article":"Love the Froggy pic, Mr Martin.  I just finished reading the bit about him in The Armageddon Rag and it was so bizarre that I initially thought you'd made him up.  After having done a bit of research I tracked down a few clips of ol' Froggy on Youtube and I have to say he's a bit scary: the gravelly voice, the creepy laugh, the relentless commitment to anarchy - he's a real agent of chaos!","siteroot":"http://www.livejournal.com","poster":"grrm","stime":"9 months ago","ctime":"July 23 2016, 21:11:39 UTC","massactions":0,"subject":"Froggy","deleted":0,"username":[{"journal_url":"https://www.facebook.com/app_scoped_user_id/10154168127740831/","striked":null,"journaltype":"I","userhead_url":"http://l-stat.livejournal.net/img/icons/facebook-16.png?v=29916?v=146.10","color":null,"noctxpopup":0,"side_alias":0,"journal":"Riley Kearns","inline_css":0,"attrs":null,"is_identity":1,"bold":1,"show_userhead":1,"username":"ext_3756308","user_alias":"","profile_url":"http://www.livejournal.com/profile?userid=78233767&t=I","alias":0}],"dname":"Riley Kearns","ctime_ts":1469308299,"tracked":0},{"shown":1,"collapsed":0,"userpic":"http://l-userpic.livejournal.com/91237832/7059164","actions":[{"allowed":1,"href":"http://grrm.livejournal.com/494398.html?thread=24796990#t24796990","name":"permalink","title":"link"},{"allowed":1,"href":"http://grrm.livejournal.com/494398.html?thread=24796990#t24796990","name":"collapse","title":"Collapse"},{"allowed":1,"href":"http://grrm.livejournal.com/494398.html?thread=24796990#t24796990","name":"expand","title":"Expand"}],"uname":"grrm","loaded":1,"p_tracked":0,"commenter_journal_base":"http://grrm.livejournal.com/","statprefix":"http://l-stat.livejournal.net","dtalkid":24796990,"talkid":96863,"thread_url":"http://grrm.livejournal.com/494398.html?thread=24796990#t24796990","above":24796734,"upictitle":"George R.R. Martin: Spain","article":"My role model.","siteroot":"http://www.livejournal.com","poster":"grrm","stime":"9 months ago","ctime":"July 23 2016, 21:29:59 UTC","parent":24796734,"massactions":0,"subject":"Re: Froggy","deleted":0,"username":[{"journal_url":"http://grrm.livejournal.com/","striked":null,"journaltype":"P","userhead_url":"http://l-stat.livejournal.net/img/userinfo_v8.svg?v=17080?v=146.10","color":null,"noctxpopup":0,"side_alias":0,"journal":"grrm","inline_css":0,"attrs":null,"is_identity":0,"bold":1,"show_userhead":1,"username":"grrm","user_alias":"","profile_url":"http://grrm.livejournal.com/profile","alias":0}],"dname":"grrm","ctime_ts":1469309399,"tracked":0},{"shown":1,"collapsed":0,"actions":[{"allowed":1,"href":"http://grrm.livejournal.com/494398.html?thread=24797246#t24797246","name":"permalink","title":"link"},{"allowed":1,"href":"http://grrm.livejournal.com/494398.html?thread=24797246#t24797246","name":"collapse","title":"Collapse"},{"allowed":1,"href":"http://grrm.livejournal.com/494398.html?thread=24797246#t24797246","name":"expand","title":"Expand"}],"uname":"ext_3443295","loaded":1,"p_tracked":0,"commenter_journal_base":"https://plus.google.com/101278675725610032025","statprefix":"http://l-stat.livejournal.net","dtalkid":24797246,"talkid":96864,"thread_url":"http://grrm.livejournal.com/494398.html?thread=24797246#t24797246","upictitle":"Uma D: pic#0","article":"Hello George, hope you are doing great!!!.<br /><br />Reading crazy stuff all over internet about TSOIAF books. Hope to hear something about TWOW from you.<br /><br />Regards,<br />Uma","siteroot":"http://www.livejournal.com","poster":"grrm","stime":"9 months ago","ctime":"July 23 2016, 21:54:46 UTC","massactions":0,"subject":"Hello George","deleted":0,"username":[{"journal_url":"https://plus.google.com/101278675725610032025","striked":null,"journaltype":"I","userhead_url":"http://l-stat.livejournal.net/img/icons/google-16.png?v=29916?v=146.10","color":null,"noctxpopup":0,"side_alias":0,"journal":"Uma D","inline_css":0,"attrs":null,"is_identity":1,"bold":1,"show_userhead":1,"username":"ext_3443295","user_alias":"","profile_url":"http://www.livejournal.com/profile?userid=77221070&t=I","alias":0}],"dname":"Uma D","ctime_ts":1469310886,"tracked":0},{"shown":1,"collapsed":0,"userpic":"http://l-userpic.livejournal.com/91237832/7059164","actions":[{"allowed":1,"href":"http://grrm.livejournal.com/494398.html?thread=24797502#t24797502","name":"permalink","title":"link"},{"allowed":1,"href":"http://grrm.livejournal.com/494398.html?thread=24797502#t24797502","name":"collapse","title":"Collapse"},{"allowed":1,"href":"http://grrm.livejournal.com/494398.html?thread=24797502#t24797502","name":"expand","title":"Expand"}],"uname":"grrm","loaded":1,"p_tracked":0,"commenter_journal_base":"http://grrm.livejournal.com/","statprefix":"http://l-stat.livejournal.net","dtalkid":24797502,"talkid":96865,"thread_url":"http://grrm.livejournal.com/494398.html?thread=24797502#t24797502","above":24797246,"upictitle":"George R.R. Martin: Spain","article":"Never believe anything you read on the internet.","siteroot":"http://www.livejournal.com","poster":"grrm","stime":"9 months ago","ctime":"July 23 2016, 22:02:39 UTC","parent":24797246,"massactions":0,"subject":"Re: Hello George","deleted":0,"username":[{"journal_url":"http://grrm.livejournal.com/","striked":null,"journaltype":"P","userhead_url":"http://l-stat.livejournal.net/img/userinfo_v8.svg?v=17080?v=146.10","color":null,"noctxpopup":0,"side_alias":0,"journal":"grrm","inline_css":0,"attrs":null,"is_identity":0,"bold":1,"show_userhead":1,"username":"grrm","user_alias":"","profile_url":"http://grrm.livejournal.com/profile","alias":0}],"dname":"grrm","ctime_ts":1469311359,"tracked":0},{"shown":1,"collapsed":0,"userpic":"http://l-userpic.livejournal.com/52265829/193288","actions":[{"allowed":1,"href":"http://grrm.livejournal.com/494398.html?thread=24798014#t24798014","name":"permalink","title":"link"},{"allowed":1,"href":"http://grrm.livejournal.com/494398.html?thread=24798014#t24798014","name":"collapse","title":"Collapse"},{"allowed":1,"href":"http://grrm.livejournal.com/494398.html?thread=24798014#t24798014","name":"expand","title":"Expand"}],"uname":"darthfrog","loaded":1,"p_tracked":0,"commenter_journal_base":"http://darthfrog.livejournal.com/","statprefix":"http://l-stat.livejournal.net","dtalkid":24798014,"talkid":96867,"thread_url":"http://grrm.livejournal.com/494398.html?thread=24798014#t24798014","upictitle":"Robert Fargher: pic#52265829","article":"So which of the two old fat guys with Greek sailor caps and wearing suspenders is the real G.R.R.M.? :-)","siteroot":"http://www.livejournal.com","poster":"grrm","stime":"9 months ago","ctime":"July 23 2016, 22:23:01 UTC","massactions":0,"subject":"Real GRRM?","deleted":0,"username":[{"journal_url":"http://darthfrog.livejournal.com/","striked":null,"journaltype":"P","userhead_url":"http://l-stat.livejournal.net/img/userinfo_v8.svg?v=17080?v=146.10","color":null,"noctxpopup":0,"side_alias":0,"journal":"darthfrog","inline_css":0,"attrs":null,"is_identity":0,"bold":1,"show_userhead":1,"username":"darthfrog","user_alias":"","profile_url":"http://darthfrog.livejournal.com/profile","alias":0}],"dname":"darthfrog","ctime_ts":1469312581,"tracked":0},{"shown":1,"collapsed":0,"actions":[{"allowed":1,"href":"http://grrm.livejournal.com/494398.html?thread=24798270#t24798270","name":"expandchilds","title":"Expand","footer":1},{"allowed":1,"href":"http://grrm.livejournal.com/494398.html?thread=24798270#t24798270","name":"permalink","title":"link"},{"allowed":1,"href":"http://grrm.livejournal.com/494398.html?thread=24798270#t24798270","name":"collapse","title":"Collapse"},{"allowed":1,"href":"http://grrm.livejournal.com/494398.html?thread=24798270#t24798270","name":"expand","title":"Expand"}],"uname":"ext_2524681","loaded":1,"p_tracked":0,"commenter_journal_base":"https://plus.google.com/118250312881037736617","statprefix":"http://l-stat.livejournal.net","dtalkid":24798270,"talkid":96868,"thread_url":"http://grrm.livejournal.com/494398.html?thread=24798270#t24798270","upictitle":"MrWalker1000: pic#0","article":"is the knight of the seven kingdoms a graphic novel? Looks super amazing. I really like it when books are adapted into graphic novels. Also, what happened to reading books with a few pages of artwork. I suppose that kind of thing wouldn't be taken seriously in the literature world, where people read stuff from James Joyce. But it wouldn't hurt to add one or two. <br /><br />How many graphic novels are there relating to your stories grrm? I kind of want to keep track of them I might end up reading them. <br /><br />I believe there is also a darktower series being adapted into a graphic novel. <br /><br />What do you think of the TV show preacher? Check it out it's based from a cul hit graphic novel called the preacher. It's going to be a huge hit by second season mark my words. Season 1 is kind of useless because it covers the backstory of the characters, instead of thea ctual story.","siteroot":"http://www.livejournal.com","poster":"grrm","stime":"9 months ago","ctime":"July 24 2016, 04:12:55 UTC","massactions":0,"subject":"","deleted":0,"username":[{"journal_url":"https://plus.google.com/118250312881037736617","striked":null,"journaltype":"I","userhead_url":"http://l-stat.livejournal.net/img/icons/google-16.png?v=29916?v=146.10","color":null,"noctxpopup":0,"side_alias":0,"journal":"MrWalker1000","inline_css":0,"attrs":null,"is_identity":1,"bold":1,"show_userhead":1,"username":"ext_2524681","user_alias":"","profile_url":"http://www.livejournal.com/profile?userid=69956814&t=I","alias":0}],"dname":"MrWalker1000","ctime_ts":1469333575,"tracked":0},{"shown":1,"collapsed":0,"userpic":"http://l-userpic.livejournal.com/91237832/7059164","actions":[{"allowed":1,"href":"http://grrm.livejournal.com/494398.html?thread=24798526#t24798526","name":"expandchilds","title":"Expand","footer":1},{"allowed":1,"href":"http://grrm.livejournal.com/494398.html?thread=24798526#t24798526","name":"permalink","title":"link"},{"allowed":1,"href":"http://grrm.livejournal.com/494398.html?thread=24798526#t24798526","name":"collapse","title":"Collapse"},{"allowed":1,"href":"http://grrm.livejournal.com/494398.html?thread=24798526#t24798526","name":"expand","title":"Expand"}],"uname":"grrm","loaded":1,"p_tracked":0,"commenter_journal_base":"http://grrm.livejournal.com/","statprefix":"http://l-stat.livejournal.net","dtalkid":24798526,"talkid":96869,"thread_url":"http://grrm.livejournal.com/494398.html?thread=24798526#t24798526","above":24798270,"upictitle":"George R.R. Martin: Spain","article":"A graphic novel?  No.  A heavily illustrated hardcover.","siteroot":"http://www.livejournal.com","poster":"grrm","stime":"9 months ago","ctime":"July 24 2016, 05:58:16 UTC","parent":24798270,"massactions":0,"subject":"","deleted":0,"username":[{"journal_url":"http://grrm.livejournal.com/","striked":null,"journaltype":"P","userhead_url":"http://l-stat.livejournal.net/img/userinfo_v8.svg?v=17080?v=146.10","color":null,"noctxpopup":0,"side_alias":0,"journal":"grrm","inline_css":0,"attrs":null,"is_identity":0,"bold":1,"show_userhead":1,"username":"grrm","user_alias":"","profile_url":"http://grrm.livejournal.com/profile","alias":0}],"dname":"grrm","ctime_ts":1469339896,"tracked":0},{"shown":1,"collapsed":1,"actions":[{"allowed":1,"href":"http://grrm.livejournal.com/494398.html?thread=24804414#t24804414","name":"permalink","title":"link"},{"allowed":1,"href":"http://grrm.livejournal.com/494398.html?thread=24804414#t24804414","name":"collapse","title":"Collapse"},{"allowed":1,"href":"http://grrm.livejournal.com/494398.html?thread=24804414#t24804414","name":"expand","title":"Expand"}],"uname":"ext_3110302","loaded":0,"p_tracked":0,"commenter_journal_base":"http://www.facebook.com/9610739","statprefix":"http://l-stat.livejournal.net","dtalkid":24804414,"talkid":96892,"thread_url":"http://grrm.livejournal.com/494398.html?thread=24804414#t24804414","above":24798526,"siteroot":"http://www.livejournal.com","poster":"grrm","stime":"9 months ago","below":24805182,"parent":24798526,"massactions":0,"subject":"","deleted":0,"username":[{"journal_url":"http://www.facebook.com/9610739","striked":null,"journaltype":"I","userhead_url":"http://l-stat.livejournal.net/img/icons/facebook-16.png?v=29916?v=146.10","color":null,"noctxpopup":0,"side_alias":0,"journal":"Ross Chaffin","inline_css":0,"attrs":null,"is_identity":1,"bold":1,"show_userhead":1,"username":"ext_3110302","user_alias":"","profile_url":"http://www.livejournal.com/profile?userid=75257790&t=I","alias":0}],"dname":"Ross Chaffin","ctime_ts":1469484818,"leafclass":"collapsed","tracked":0},{"shown":1,"collapsed":1,"actions":[{"allowed":1,"href":"http://grrm.livejournal.com/494398.html?thread=24805182#t24805182","name":"permalink","title":"link"},{"allowed":1,"href":"http://grrm.livejournal.com/494398.html?thread=24805182#t24805182","name":"collapse","title":"Collapse"},{"allowed":1,"href":"http://grrm.livejournal.com/494398.html?thread=24805182#t24805182","name":"expand","title":"Expand"}],"uname":"ext_2524681","loaded":0,"p_tracked":0,"commenter_journal_base":"https://plus.google.com/118250312881037736617","statprefix":"http://l-stat.livejournal.net","dtalkid":24805182,"talkid":96895,"thread_url":"http://grrm.livejournal.com/494398.html?thread=24805182#t24805182","above":24804414,"siteroot":"http://www.livejournal.com","poster":"grrm","stime":"9 months ago","parent":24798526,"massactions":0,"subject":"","deleted":0,"username":[{"journal_url":"https://plus.google.com/118250312881037736617","striked":null,"journaltype":"I","userhead_url":"http://l-stat.livejournal.net/img/icons/google-16.png?v=29916?v=146.10","color":null,"noctxpopup":0,"side_alias":0,"journal":"MrWalker1000","inline_css":0,"attrs":null,"is_identity":1,"bold":1,"show_userhead":1,"username":"ext_2524681","user_alias":"","profile_url":"http://www.livejournal.com/profile?userid=69956814&t=I","alias":0}],"dname":"MrWalker1000","ctime_ts":1469516833,"leafclass":"collapsed","tracked":0},{"shown":1,"collapsed":0,"userpic":"http://l-userpic.livejournal.com/124302622/73354478","actions":[{"allowed":1,"href":"http://grrm.livejournal.com/494398.html?thread=24798782#t24798782","name":"permalink","title":"link"},{"allowed":1,"href":"http://grrm.livejournal.com/494398.html?thread=24798782#t24798782","name":"collapse","title":"Collapse"},{"allowed":1,"href":"http://grrm.livejournal.com/494398.html?thread=24798782#t24798782","name":"expand","title":"Expand"}],"uname":"ext_2902334","loaded":1,"p_tracked":0,"commenter_journal_base":"http://twitter.com/ADragonDemands","statprefix":"http://l-stat.livejournal.net","dtalkid":24798782,"talkid":96870,"thread_url":"http://grrm.livejournal.com/494398.html?thread=24798782#t24798782","upictitle":"The Dragon Demands: pic#124302622","article":"I'm submitting a panel to the New York Comic Con but doubt they'll fit me in; \"Gender and Sexuality in Game of Thrones\" - based on 1 - copious knowledge about the show from being an Admin on the Game of Thrones Wiki, and 2 - I actually have a master's degree in medieval history in real life.  <br /><br />Last year was odd; they didn't really have any programming for the Loras and Obara actors to do so they just hung around in the autograph section *all* of Saturday and Sunday; which worked for me because it meant they were free to be interviewed.  <br /><br />SDCC is too crowded though, I went once and didn't like it; NYCC closer to home.  <br /><br />Other fun fact:  every year the Wikia group has a fan poll for \"Favorite Fantasy Food\"; all the different wikis submit a fictional food and the one that wins, they make a real-life approximation of it and hand it out at a booth at NYCC.  This year our submission was \"Frey Pie\"....didn't make it past the first round of voting, though.  Crud.  ","siteroot":"http://www.livejournal.com","poster":"grrm","stime":"9 months ago","ctime":"July 24 2016, 06:43:58 UTC","massactions":0,"subject":"Looking forward to NYCC","deleted":0,"username":[{"journal_url":"http://twitter.com/ADragonDemands","striked":null,"journaltype":"I","userhead_url":"http://l-stat.livejournal.net/img/icons/twitter-16.png?v=29916?v=146.10","color":null,"noctxpopup":0,"side_alias":0,"journal":"ADragonDemands","inline_css":0,"attrs":null,"is_identity":1,"bold":1,"show_userhead":1,"username":"ext_2902334","user_alias":"","profile_url":"http://www.livejournal.com/profile?userid=73354478&t=I","alias":0}],"dname":"ADragonDemands","ctime_ts":1469342638,"tracked":0},{"shown":1,"collapsed":0,"userpic":"http://l-userpic.livejournal.com/124081839/72492018","actions":[{"allowed":1,"href":"http://grrm.livejournal.com/494398.html?thread=24799038#t24799038","name":"permalink","title":"link"},{"allowed":1,"href":"http://grrm.livejournal.com/494398.html?thread=24799038#t24799038","name":"collapse","title":"Collapse"},{"allowed":1,"href":"http://grrm.livejournal.com/494398.html?thread=24799038#t24799038","name":"expand","title":"Expand"}],"uname":"missmatchedeyes","loaded":1,"p_tracked":0,"commenter_journal_base":"http://missmatchedeyes.livejournal.com/","statprefix":"http://l-stat.livejournal.net","dtalkid":24799038,"talkid":96871,"thread_url":"http://grrm.livejournal.com/494398.html?thread=24799038#t24799038","upictitle":"missmatchedeyes: pic#124081839","article":"I can't wait to get the calendar, George! <br />I was wondering who is the artist for the illustrated copy of Game of Thrones that is coming out in October? Thanks!","siteroot":"http://www.livejournal.com","poster":"grrm","stime":"9 months ago","ctime":"July 24 2016, 11:54:07 UTC","massactions":0,"subject":"Artists","deleted":0,"username":[{"journal_url":"http://missmatchedeyes.livejournal.com/","striked":null,"journaltype":"P","userhead_url":"http://l-stat.livejournal.net/img/userinfo_v8.svg?v=17080?v=146.10","color":null,"noctxpopup":0,"side_alias":0,"journal":"missmatchedeyes","inline_css":0,"attrs":null,"is_identity":0,"bold":1,"show_userhead":1,"username":"missmatchedeyes","user_alias":"","profile_url":"http://missmatchedeyes.livejournal.com/profile","alias":0}],"dname":"missmatchedeyes","ctime_ts":1469361247,"tracked":0},{"shown":1,"collapsed":0,"userpic":"http://l-userpic.livejournal.com/123371686/70873652","actions":[{"allowed":1,"href":"http://grrm.livejournal.com/494398.html?thread=24799294#t24799294","name":"permalink","title":"link"},{"allowed":1,"href":"http://grrm.livejournal.com/494398.html?thread=24799294#t24799294","name":"collapse","title":"Collapse"},{"allowed":1,"href":"http://grrm.livejournal.com/494398.html?thread=24799294#t24799294","name":"expand","title":"Expand"}],"uname":"ext_2587046","loaded":1,"p_tracked":0,"commenter_journal_base":"https://www.facebook.com/profile.php?id=2246029","statprefix":"http://l-stat.livejournal.net","dtalkid":24799294,"talkid":96872,"thread_url":"http://grrm.livejournal.com/494398.html?thread=24799294#t24799294","upictitle":"Frank Probst: pic#123371686","article":"Saturday Night Live did a pretty good impersonation of you.  That skit was hilarious!","siteroot":"http://www.livejournal.com","poster":"grrm","stime":"9 months ago","ctime":"July 24 2016, 13:58:09 UTC","massactions":0,"subject":"Stunt doubles","deleted":0,"username":[{"journal_url":"https://www.facebook.com/profile.php?id=2246029","striked":null,"journaltype":"I","userhead_url":"http://l-stat.livejournal.net/img/icons/facebook-16.png?v=29916?v=146.10","color":null,"noctxpopup":0,"side_alias":0,"journal":"Frank Probst","inline_css":0,"attrs":null,"is_identity":1,"bold":1,"show_userhead":1,"username":"ext_2587046","user_alias":"","profile_url":"http://www.livejournal.com/profile?userid=70873652&t=I","alias":0}],"dname":"Frank Probst","ctime_ts":1469368689,"tracked":0},{"shown":1,"collapsed":0,"userpic":"http://l-userpic.livejournal.com/117590782/50236298","actions":[{"allowed":1,"href":"http://grrm.livejournal.com/494398.html?thread=24799550#t24799550","name":"permalink","title":"link"},{"allowed":1,"href":"http://grrm.livejournal.com/494398.html?thread=24799550#t24799550","name":"collapse","title":"Collapse"},{"allowed":1,"href":"http://grrm.livejournal.com/494398.html?thread=24799550#t24799550","name":"expand","title":"Expand"}],"uname":"noldaker","loaded":1,"p_tracked":0,"commenter_journal_base":"http://noldaker.livejournal.com/","statprefix":"http://l-stat.livejournal.net","dtalkid":24799550,"talkid":96873,"thread_url":"http://grrm.livejournal.com/494398.html?thread=24799550#t24799550","upictitle":"Nikki O: pic#117590782","article":"Watching a cast GoT interview from March 22, 2013 you were in...As a writer loved your response when interviewer asked cast and you, \"If you could play any other character which one?\" You're response,\"I play them all\" -Often wonder if people realize this. <br /><br />Your photo look-a-like -is good match - reminds me of the annual  Ernest Hemingway contest in Key West. <br /><br />Enjoy your summer!!! <br /><br /> ","siteroot":"http://www.livejournal.com","poster":"grrm","stime":"9 months ago","ctime":"July 24 2016, 14:19:30 UTC","massactions":0,"subject":"Your response about writers","deleted":0,"username":[{"journal_url":"http://noldaker.livejournal.com/","striked":null,"journaltype":"P","userhead_url":"http://l-stat.livejournal.net/img/userinfo_v8.svg?v=17080?v=146.10","color":null,"noctxpopup":0,"side_alias":0,"journal":"noldaker","inline_css":0,"attrs":null,"is_identity":0,"bold":1,"show_userhead":1,"username":"noldaker","user_alias":"","profile_url":"http://noldaker.livejournal.com/profile","alias":0}],"dname":"noldaker","ctime_ts":1469369970,"tracked":0},{"shown":1,"collapsed":0,"actions":[{"allowed":1,"href":"http://grrm.livejournal.com/494398.html?thread=24799806#t24799806","name":"expandchilds","title":"Expand","footer":1},{"allowed":1,"href":"http://grrm.livejournal.com/494398.html?thread=24799806#t24799806","name":"permalink","title":"link"},{"allowed":1,"href":"http://grrm.livejournal.com/494398.html?thread=24799806#t24799806","name":"collapse","title":"Collapse"},{"allowed":1,"href":"http://grrm.livejournal.com/494398.html?thread=24799806#t24799806","name":"expand","title":"Expand"}],"uname":"phildotidotp","loaded":1,"p_tracked":0,"commenter_journal_base":"http://phildotidotp.livejournal.com/","statprefix":"http://l-stat.livejournal.net","dtalkid":24799806,"talkid":96874,"thread_url":"http://grrm.livejournal.com/494398.html?thread=24799806#t24799806","upictitle":"phildotidotp: pic#0","article":"Slightly related to your post because they have a presence at Comic-con, I read that Skybound are to adapt Roger Zelazny's <i>Chronicles of Amber</i> for television. There is more info available on their website.<br /><br />Could be the next <i>GoT</i>. What do you think?<br /><br />Phil","siteroot":"http://www.livejournal.com","poster":"grrm","stime":"9 months ago","ctime":"July 24 2016, 14:44:13 UTC","massactions":0,"subject":"Amber","deleted":0,"username":[{"journal_url":"http://phildotidotp.livejournal.com/","striked":null,"journaltype":"P","userhead_url":"http://l-stat.livejournal.net/img/userinfo_v8.svg?v=17080?v=146.10","color":null,"noctxpopup":0,"side_alias":0,"journal":"phildotidotp","inline_css":0,"attrs":null,"is_identity":0,"bold":1,"show_userhead":1,"username":"phildotidotp","user_alias":"","profile_url":"http://phildotidotp.livejournal.com/profile","alias":0}],"dname":"phildotidotp","ctime_ts":1469371453,"tracked":0},{"shown":1,"collapsed":0,"userpic":"http://l-userpic.livejournal.com/91237832/7059164","actions":[{"allowed":1,"href":"http://grrm.livejournal.com/494398.html?thread=24800062#t24800062","name":"expandchilds","title":"Expand","footer":1},{"allowed":1,"href":"http://grrm.livejournal.com/494398.html?thread=24800062#t24800062","name":"permalink","title":"link"},{"allowed":1,"href":"http://grrm.livejournal.com/494398.html?thread=24800062#t24800062","name":"collapse","title":"Collapse"},{"allowed":1,"href":"http://grrm.livejournal.com/494398.html?thread=24800062#t24800062","name":"expand","title":"Expand"}],"uname":"grrm","loaded":1,"p_tracked":0,"commenter_journal_base":"http://grrm.livejournal.com/","statprefix":"http://l-stat.livejournal.net","dtalkid":24800062,"talkid":96875,"thread_url":"http://grrm.livejournal.com/494398.html?thread=24800062#t24800062","above":24799806,"upictitle":"George R.R. Martin: Spain","article":"I think Amber will be fabulous... so long as they do not stray too far from Roger's books.   ","siteroot":"http://www.livejournal.com","poster":"grrm","stime":"9 months ago","ctime":"July 24 2016, 18:51:08 UTC","parent":24799806,"massactions":0,"subject":"Re: Amber","deleted":0,"username":[{"journal_url":"http://grrm.livejournal.com/","striked":null,"journaltype":"P","userhead_url":"http://l-stat.livejournal.net/img/userinfo_v8.svg?v=17080?v=146.10","color":null,"noctxpopup":0,"side_alias":0,"journal":"grrm","inline_css":0,"attrs":null,"is_identity":0,"bold":1,"show_userhead":1,"username":"grrm","user_alias":"","profile_url":"http://grrm.livejournal.com/profile","alias":0}],"dname":"grrm","ctime_ts":1469386268,"tracked":0},{"shown":1,"collapsed":1,"actions":[{"allowed":1,"href":"http://grrm.livejournal.com/494398.html?thread=24801086#t24801086","name":"permalink","title":"link"},{"allowed":1,"href":"http://grrm.livejournal.com/494398.html?thread=24801086#t24801086","name":"collapse","title":"Collapse"},{"allowed":1,"href":"http://grrm.livejournal.com/494398.html?thread=24801086#t24801086","name":"expand","title":"Expand"}],"uname":"jacobsb2440","loaded":0,"p_tracked":0,"commenter_journal_base":"http://jacobsb2440.livejournal.com/","statprefix":"http://l-stat.livejournal.net","dtalkid":24801086,"talkid":96879,"thread_url":"http://grrm.livejournal.com/494398.html?thread=24801086#t24801086","above":24800062,"siteroot":"http://www.livejournal.com","poster":"grrm","stime":"9 months ago","parent":24800062,"massactions":0,"subject":"RE: Re: Amber","deleted":0,"username":[{"journal_url":"http://jacobsb2440.livejournal.com/","striked":null,"journaltype":"P","userhead_url":"http://l-stat.livejournal.net/img/userinfo_v8.svg?v=17080?v=146.10","color":null,"noctxpopup":0,"side_alias":0,"journal":"jacobsb2440","inline_css":0,"attrs":null,"is_identity":0,"bold":1,"show_userhead":1,"username":"jacobsb2440","user_alias":"","profile_url":"http://jacobsb2440.livejournal.com/profile","alias":0}],"dname":"jacobsb2440","ctime_ts":1469407820,"leafclass":"collapsed","tracked":0},{"shown":1,"collapsed":0,"userpic":"http://l-userpic.livejournal.com/120142958/51623257","actions":[{"allowed":1,"href":"http://grrm.livejournal.com/494398.html?thread=24800318#t24800318","name":"permalink","title":"link"},{"allowed":1,"href":"http://grrm.livejournal.com/494398.html?thread=24800318#t24800318","name":"collapse","title":"Collapse"},{"allowed":1,"href":"http://grrm.livejournal.com/494398.html?thread=24800318#t24800318","name":"expand","title":"Expand"}],"uname":"sourbillytipton","loaded":1,"p_tracked":0,"commenter_journal_base":"http://sourbillytipton.livejournal.com/","statprefix":"http://l-stat.livejournal.net","dtalkid":24800318,"talkid":96876,"thread_url":"http://grrm.livejournal.com/494398.html?thread=24800318#t24800318","upictitle":"sourbillytipton: pic#120142958","article":"was shown at Comicon, looks great.  It comes out in March 2017.  Will Son of Kong be finished before then?<br /><br />I have a strong feeling of confidence it will.  ","siteroot":"http://www.livejournal.com","poster":"grrm","stime":"9 months ago","ctime":"July 24 2016, 20:10:09 UTC","massactions":0,"subject":"KONG: Skull Island","deleted":0,"username":[{"journal_url":"http://sourbillytipton.livejournal.com/","striked":null,"journaltype":"P","userhead_url":"http://l-stat.livejournal.net/img/userinfo_v8.svg?v=17080?v=146.10","color":null,"noctxpopup":0,"side_alias":0,"journal":"sourbillytipton","inline_css":0,"attrs":null,"is_identity":0,"bold":1,"show_userhead":1,"username":"sourbillytipton","user_alias":"","profile_url":"http://sourbillytipton.livejournal.com/profile","alias":0}],"dname":"sourbillytipton","ctime_ts":1469391009,"tracked":0}]}